rootshell_platform_api/__init__.py
rootshell_platform_api/adapters/AssetGroupAssetsAPIClient.py
rootshell_platform_api/adapters/AssetGroupsAPIClient.py
rootshell_platform_api/adapters/AssetTagsAPIClient.py
rootshell_platform_api/adapters/AssetsAPIClient.py
rootshell_platform_api/adapters/BaseAPIClient.py
rootshell_platform_api/adapters/CompaniesAPIClient.py
rootshell_platform_api/adapters/IssueCommentsAPIClient.py
rootshell_platform_api/adapters/IssuesAPIClient.py
rootshell_platform_api/adapters/MergeSettingsAPIClient.py
rootshell_platform_api/adapters/PhaseHostIssuesAPIClient.py
rootshell_platform_api/adapters/PhaseHostsAPIClient.py
rootshell_platform_api/adapters/PhaseIssuesAPIClient.py
rootshell_platform_api/adapters/PhaseReviewersAPIClient.py
rootshell_platform_api/adapters/PhaseTagsAPIClient.py
rootshell_platform_api/adapters/PhaseTestersAPIClient.py
rootshell_platform_api/adapters/PhasesAPIClient.py
rootshell_platform_api/adapters/ProjectCommentsAPIClient.py
rootshell_platform_api/adapters/ProjectTagsAPIClient.py
rootshell_platform_api/adapters/ProjectsAPIClient.py
rootshell_platform_api/adapters/TagsAPIClient.py
rootshell_platform_api/adapters/TestTypesAPIClient.py
rootshell_platform_api/adapters/UsersAPIClient.py
rootshell_platform_api/adapters/__init__.py
rootshell_platform_api/cli.py
rootshell_platform_api/cli_commands/__init__.py
rootshell_platform_api/cli_commands/asset_group_assets/__init__.py
rootshell_platform_api/cli_commands/asset_group_assets/get_paginated.py
rootshell_platform_api/cli_commands/asset_group_assets/update.py
rootshell_platform_api/cli_commands/asset_groups/__init__.py
rootshell_platform_api/cli_commands/asset_groups/create.py
rootshell_platform_api/cli_commands/asset_groups/delete.py
rootshell_platform_api/cli_commands/asset_groups/get_paginated.py
rootshell_platform_api/cli_commands/asset_groups/get_single.py
rootshell_platform_api/cli_commands/asset_groups/update.py
rootshell_platform_api/cli_commands/asset_tags/__init__.py
rootshell_platform_api-0.2.0.dist-info/METADATA
rootshell_platform_api-0.2.0.dist-info/WHEEL
rootshell_platform_api-0.2.0.dist-info/entry_points.txt
rootshell_platform_api-0.2.0.dist-info/RECORD
